cacti/__init__.py
cacti/dataloader.py
cacti/pipeline.py
cacti/test_box.py
cacti-0.2.dist-info/METADATA
cacti-0.2.dist-info/RECORD
cacti-0.2.dist-info/WHEEL
cacti-0.2.dist-info/top_level.txt
