Metadata-Version: 2.1
Name: cacti
Version: 0.2
Summary: This is a torch data load package.
Home-page: https://github.com/wanlishun66668/datacpp
Author: UCAS wang lishun
Author-email: 690332121@qq.com
License: UNKNOWN
Platform: UNKNOWN
